poet_plugin/__init__.py
poet_plugin/plugin.py
poet_plugin-0.1.2.dist-info/entry_points.txt
poet_plugin-0.1.2.dist-info/LICENSE
poet_plugin-0.1.2.dist-info/WHEEL
poet_plugin-0.1.2.dist-info/METADATA
poet_plugin-0.1.2.dist-info/RECORD
