Metadata-Version: 2.1
Name: poet-plugin
Version: 0.1.2
Summary: A Poetry plugin to enable exclusivity between groups
License: MIT
Author: Idan Tene
Author-email: idan.tene@gmail.com
Requires-Python: >=3.7,<4.0
Classifier: License :: OSI Approved :: MIT License
Classifier: Programming Language :: Python :: 3
Classifier: Programming Language :: Python :: 3.7
Classifier: Programming Language :: Python :: 3.8
Classifier: Programming Language :: Python :: 3.9
Classifier: Programming Language :: Python :: 3.10
Requires-Dist: poetry (>=1.2.0,<2.0.0)
